poetry_artifactregistry_plugin/__init__.py
poetry_artifactregistry_plugin/gcloud.py
poetry_artifactregistry_plugin/plugins.py
poetry_artifactregistry_plugin-0.1.0.dist-info/entry_points.txt
poetry_artifactregistry_plugin-0.1.0.dist-info/WHEEL
poetry_artifactregistry_plugin-0.1.0.dist-info/METADATA
poetry_artifactregistry_plugin-0.1.0.dist-info/RECORD
