Metadata-Version: 2.1
Name: poetry-artifactregistry-plugin
Version: 0.1.0
Summary: This repository is a plugin to configure poetry and Google Artifact Registry authentication
License: MIT
Author: Julien Klaer
Author-email: klaer.julien@gmail.com
Requires-Python: >=3.7,<4.0
Classifier: License :: OSI Approved :: MIT License
Classifier: Programming Language :: Python :: 3
Classifier: Programming Language :: Python :: 3.7
Classifier: Programming Language :: Python :: 3.8
Classifier: Programming Language :: Python :: 3.9
Classifier: Programming Language :: Python :: 3.10
Requires-Dist: keyrings.google-artifactregistry-auth (>=1.0.0,<2.0.0)
Requires-Dist: poetry (>=1.2.0b1dev0,<2.0.0)
